README.md
setup.cfg
setup.py
bot4/pars_packets_name.py
bot4.egg-info/PKG-INFO
bot4.egg-info/SOURCES.txt
bot4.egg-info/dependency_links.txt
bot4.egg-info/requires.txt
bot4.egg-info/top_level.txt
bot4/net/__init__.py
bot4/net/auth.py
bot4/net/crypto.py
bot4/protocol/protocolbase.py
bot4/protocol/protocols.py
bot4/types/__init__.py
bot4/types/chat.py
bot4/types/chunk.py
bot4/types/nbt.py
bot4/types/registry.py
bot4/types/settings.py
bot4/types/uuid.py
bot4/types/buffer/__init__.py
bot4/types/buffer/v1_13.py
bot4/types/buffer/v1_13_2.py
bot4/types/buffer/v1_14.py
bot4/types/buffer/v1_19.py
bot4/types/buffer/v1_19_1.py
bot4/types/buffer/v1_7.py
bot4/types/buffer/v1_9.py
bot4/versions/754.json
bot4/versions/757.json
bot4/versions/packets.py
bot4/versions/test.py
bot4/versions/version_protocols.json