Metadata-Version: 2.1
Name: bot4
Version: 0.0.7
Summary: This is a module for creating bots
Home-page: https://github.com/Jeelesk/bot4
Author: Jeelesk
Author-email: eywevynriimnetyiu@gmail.com
Classifier: Programming Language :: Python :: 3.11
Classifier: License :: OSI Approved :: MIT License
Classifier: Operating System :: OS Independent
Requires-Python: >=3.10
